rabbitmq_subprocess_client/__init__.py
rabbitmq_subprocess_client/consumer.py
rabbitmq_subprocess_client/runner.py
rabbitmq_subprocess_client/utils.py
rabbitmq_subprocess_client-1.0.1.dist-info/METADATA
rabbitmq_subprocess_client-1.0.1.dist-info/WHEEL
rabbitmq_subprocess_client-1.0.1.dist-info/RECORD
