Metadata-Version: 2.1
Name: rabbitmq-subprocess-client
Version: 1.0.1
Summary: rabbitmq-subprocess-client is a RabbitMQ client (based on `pika`) spawning tasks as subprocess, allowing handling segfault gracefully.
Home-page: https://github.com/bimdata/rabbitmq-subprocess-client
License: MIT
Author: amoki
Author-email: hugo@bimdata.io
Requires-Python: >=3.8,<4.0
Classifier: License :: OSI Approved :: MIT License
Classifier: Programming Language :: Python :: 3
Classifier: Programming Language :: Python :: 3.8
Classifier: Programming Language :: Python :: 3.9
Classifier: Programming Language :: Python :: 3.10
Classifier: Programming Language :: Python :: 3.11
Requires-Dist: pika (>=1.2.0,<2.0.0)
Requires-Dist: reorder-python-imports (>=3.9.0,<4.0.0)
Project-URL: Repository, https://github.com/bimdata/rabbitmq-subprocess-client
